pytest_astodojo.py
astodojo/ASTODOJO-AGENT-HELPER.md
astodojo/__init__.py
astodojo/cli.py
astodojo/config.py
astodojo/core.py
astodojo/github.py
astodojo-0.3.0.dist-info/licenses/LICENSE
test/run_autopilot.py
test/fixtures/complex_structure.py
test/fixtures/edge_cases.py
test/fixtures/simple_todos.py
test/fixtures/exclude_test/build/generated.py
test/fixtures/exclude_test/src/main.py
test/fixtures/exclude_test/tests/test_main.py
test/suites/autopilot_test.py
tests/__init__.py
tests/test_cli.py
tests/test_config.py
tests/test_core.py
tests/test_github.py
astodojo-0.3.0.dist-info/METADATA
astodojo-0.3.0.dist-info/WHEEL
astodojo-0.3.0.dist-info/entry_points.txt
astodojo-0.3.0.dist-info/top_level.txt
astodojo-0.3.0.dist-info/RECORD
