Metadata-Version: 2.4
Name: astodojo
Version: 0.3.0
Summary: ASTODOJO: Intelligent TODO scanner for Python codebases
License-Expression: MIT
Project-URL: Homepage, https://github.com/seanmcdonald/astodojo
Project-URL: Repository, https://github.com/seanmcdonald/astodojo
Project-URL: Issues, https://github.com/seanmcdonald/astodojo/issues
Classifier: Development Status :: 3 - Alpha
Classifier: Intended Audience :: Developers
Classifier: Programming Language :: Python :: 3
Classifier: Programming Language :: Python :: 3.8
Classifier: Programming Language :: Python :: 3.9
Classifier: Programming Language :: Python :: 3.10
Classifier: Programming Language :: Python :: 3.11
Classifier: Programming Language :: Python :: 3.12
Classifier: Topic :: Software Development :: Quality Assurance
Classifier: Topic :: Utilities
Requires-Python: >=3.8
License-File: LICENSE
Requires-Dist: click>=8.0.0
Requires-Dist: colorama>=0.4.6
Requires-Dist: rich>=13.0.0
Requires-Dist: PyYAML>=6.0
Requires-Dist: requests>=2.28.0
Dynamic: license-file
